cookiemilk/__init__.py
cookiemilk/average_graph.py
cookiemilk/calc_gcent.py
cookiemilk/calc_graphical_matching.py
cookiemilk/calc_surface_matching.py
cookiemilk/calc_tversky.py
cookiemilk/cmap2graph.py
cookiemilk/draw.py
cookiemilk/numerical_sim.py
cookiemilk/pathfinder_network.py
cookiemilk/quick_analysis.py
cookiemilk/text2graph.py
cookiemilk-0.1.1.dist-info/LICENSE
cookiemilk-0.1.1.dist-info/METADATA
cookiemilk-0.1.1.dist-info/WHEEL
cookiemilk-0.1.1.dist-info/top_level.txt
cookiemilk-0.1.1.dist-info/RECORD
