Metadata-Version: 2.1
Name: cookiemilk
Version: 0.1.1
Summary: An easy-to-use Python package to process knowledge structure data automatically
Home-page: https://github.com/weiziqianpsych/cookiemilk
Author: Ziqian Wei
Author-email: weiziqianpsych@outlook.com
Requires-Python: >=3.6
License-File: LICENSE
Requires-Dist: numpy
Requires-Dist: pywebview
Requires-Dist: networkx
